setup.py
vehiclesfortest/__init__.py
vehiclesfortest/app.py
vehiclesfortest.egg-info/PKG-INFO
vehiclesfortest.egg-info/SOURCES.txt
vehiclesfortest.egg-info/dependency_links.txt
vehiclesfortest.egg-info/not-zip-safe
vehiclesfortest.egg-info/top_level.txt