Metadata-Version: 1.0
Name: vehiclesfortest
Version: 0.1
Summary: Testing usage of packaging
Home-page: UNKNOWN
Author: Sufian
Author-email: sufian@things.school
License: UNKNOWN
Platform: UNKNOWN
